MANIFEST.in
README.md
requirements.txt
setup.py
featurize_runtime/__init__.py
featurize_runtime/cli.py
featurize_runtime/constants.py
featurize_runtime/plugins.py
featurize_runtime/process_env.py
featurize_runtime/rpc.py
featurize_runtime/run.py
featurize_runtime/training_process.py
featurize_runtime.egg-info/PKG-INFO
featurize_runtime.egg-info/SOURCES.txt
featurize_runtime.egg-info/dependency_links.txt
featurize_runtime.egg-info/entry_points.txt
featurize_runtime.egg-info/requires.txt
featurize_runtime.egg-info/top_level.txt