Metadata-Version: 2.1
Name: featurize-runtime
Version: 0.0.9
Summary: Featurize runtime
Home-page: UNKNOWN
Author: 
License: UNKNOWN
Platform: UNKNOWN
